eccv_caption/__init__.py
eccv_caption/_metrics.py
eccv_caption/metrics.py
eccv_caption/data/coco_test_ids.npy
eccv_caption/data/cxc_caption_to_image.json
eccv_caption/data/cxc_image_to_caption.json
eccv_caption/data/eccv_caption_to_image.json
eccv_caption/data/eccv_image_to_caption.json
eccv_caption/data/original_caption_to_image.json
eccv_caption/data/original_image_to_caption.json
eccv_caption-0.1.0.dist-info/LICENSE
eccv_caption-0.1.0.dist-info/METADATA
eccv_caption-0.1.0.dist-info/NOTICE
eccv_caption-0.1.0.dist-info/WHEEL
eccv_caption-0.1.0.dist-info/top_level.txt
eccv_caption-0.1.0.dist-info/RECORD
