Metadata-Version: 2.1
Name: eccv-caption
Version: 0.1.0
Summary: A PyThon wrapper for Extended COCO Validation (ECCV) Caption dataset
Home-page: https://github.com/naver-ai/eccv-caption
Author: Sanghyuk Chun
Author-email: sanghyuk.chun@gmail.com
License: UNKNOWN
Platform: UNKNOWN
Classifier: Programming Language :: Python :: 3
Classifier: License :: OSI Approved :: MIT License
Classifier: Operating System :: OS Independent
License-File: LICENSE
License-File: NOTICE
